{"program": "def solve_c444b776(I):\n    x1 = objects(I, T, F, F)\n    x2 = colorfilter(x1, ZERO)\n    x3 = argmin(x2, size)\n    x4 = backdrop(x3)\n    x5 = toobject(x4, I)\n    x6 = normalize(x5)\n    x7 = lbind(shift, x6)\n    x8 = compose(x7, ulcorner)\n    x9 = remove(x3, x2)\n    x10 = mapply(x8, x9)\n    O = paint(I, x10)\n    return O\n", "training_examples": [{"input": [[0, 0, 0, 0, 0, 0, 0, 0, 0], [0, 0, 0, 0, 0, 5, 0, 2, 0], [0, 0, 1, 0, 0, 0, 0, 0, 0], [0, 0, 0, 0, 0, 0, 0, 0, 0], [0, 0, 0, 0, 1, 0, 0, 0, 0], [0, 0, 1, 0, 0, 0, 0, 0, 0], [0, 0, 2, 0, 0, 0, 0, 2, 0], [0, 2, 0, 0, 0, 5, 5, 0, 0], [0, 0, 0, 0, 0, 0, 0, 0, 0], [4, 4, 4, 4, 4, 4, 4, 4, 4], [0, 0, 0, 0, 0, 0, 0, 0, 0], [0, 0, 0, 0, 0, 0, 0, 0, 0], [0, 0, 0, 0, 0, 0, 0, 0, 0], [0, 0, 0, 0, 0, 0, 0, 0, 0], [0, 0, 0, 0, 0, 0, 0, 0, 0], [0, 0, 0, 0, 0, 0, 0, 0, 0], [0, 0, 0, 0, 0, 0, 0, 0, 0], [0, 0, 0, 0, 0, 0, 0, 0, 0], [0, 0, 0, 0, 0, 0, 0, 0, 0]], "output": [[0, 0, 0, 0, 0, 0, 0, 0, 0], [0, 0, 0, 0, 0, 5, 0, 2, 0], [0, 0, 1, 0, 0, 0, 0, 0, 0], [0, 0, 0, 0, 0, 0, 0, 0, 0], [0, 0, 0, 0, 1, 0, 0, 0, 0], [0, 0, 1, 0, 0, 0, 0, 0, 0], [0, 0, 2, 0, 0, 0, 0, 2, 0], [0, 2, 0, 0, 0, 5, 5, 0, 0], [0, 0, 0, 0, 0, 0, 0, 0, 0], [4, 4, 4, 4, 4, 4, 4, 4, 4], [0, 0, 0, 0, 0, 0, 0, 0, 0], [0, 0, 0, 0, 0, 5, 0, 2, 0], [0, 0, 1, 0, 0, 0, 0, 0, 0], [0, 0, 0, 0, 0, 0, 0, 0, 0], [0, 0, 0, 0, 1, 0, 0, 0, 0], [0, 0, 1, 0, 0, 0, 0, 0, 0], [0, 0, 2, 0, 0, 0, 0, 2, 0], [0, 2, 0, 0, 0, 5, 5, 0, 0], [0, 0, 0, 0, 0, 0, 0, 0, 0]]}, {"input": [[0, 0, 0, 0, 0, 0, 0, 0, 0, 4, 0, 0, 0, 0, 0, 0, 0, 0, 0], [0, 0, 0, 0, 0, 0, 0, 0, 0, 4, 0, 0, 0, 0, 0, 0, 0, 0, 0], [0, 0, 0, 0, 0, 0, 0, 0, 0, 4, 0, 0, 0, 0, 0, 0, 0, 0, 0], [0, 0, 0, 0, 0, 0, 0, 0, 0, 4, 0, 0, 0, 0, 0, 0, 0, 0, 0], [0, 0, 0, 0, 0, 0, 0, 0, 0, 4, 0, 0, 0, 0, 0, 0, 0, 0, 0], [0, 0, 0, 0, 0, 0, 0, 0, 0, 4, 0, 0, 0, 0, 0, 0, 0, 0, 0], [0, 0, 0, 0, 0, 0, 0, 0, 0, 4, 0, 0, 0, 0, 0, 0, 0, 0, 0], [0, 0, 0, 0, 0, 0, 0, 0, 0, 4, 0, 0, 0, 0, 0, 0, 0, 0, 0], [0, 0, 0, 0, 0, 0, 0, 0, 0, 4, 0, 0, 0, 0, 0, 0, 0, 0, 0], [4, 4, 4, 4, 4, 4, 4, 4, 4, 4, 4, 4, 4, 4, 4, 4, 4, 4, 4], [0, 0, 0, 0, 0, 0, 0, 0, 0, 4, 0, 0, 0, 0, 0, 0, 0, 0, 0], [0, 0, 0, 0, 0, 7, 0, 0, 0, 4, 0, 0, 0, 0, 0, 0, 0, 0, 0], [0, 0, 0, 2, 0, 0, 0, 0, 0, 4, 0, 0, 0, 0, 0, 0, 0, 0, 0], [0, 0, 2, 0, 0, 0, 0, 0, 0, 4, 0, 0, 0, 0, 0, 0, 0, 0, 0], [0, 3, 0, 0, 0, 3, 0, 0, 0, 4, 0, 0, 0, 0, 0, 0, 0, 0, 0], [0, 0, 0, 0, 0, 0, 0, 0, 0, 4, 0, 0, 0, 0, 0, 0, 0, 0, 0], [0, 0, 0, 8, 7, 0, 0, 0, 0, 4, 0, 0, 0, 0, 0, 0, 0, 0, 0], [0, 0, 0, 0, 8, 0, 0, 3, 0, 4, 0, 0, 0, 0, 0, 0, 0, 0, 0], [0, 7, 0, 0, 0, 0, 0, 0, 0, 4, 0, 0, 0, 0, 0, 0, 0, 0, 0]], "output": [[0, 0, 0, 0, 0, 0, 0, 0, 0, 4, 0, 0, 0, 0, 0, 0, 0, 0, 0], [0, 0, 0, 0, 0, 7, 0, 0, 0, 4, 0, 0, 0, 0, 0, 7, 0, 0, 0], [0, 0, 0, 2, 0, 0, 0, 0, 0, 4, 0, 0, 0, 2, 0, 0, 0, 0, 0], [0, 0, 2, 0, 0, 0, 0, 0, 0, 4, 0, 0, 2, 0, 0, 0, 0, 0, 0], [0, 3, 0, 0, 0, 3, 0, 0, 0, 4, 0, 3, 0, 0, 0, 3, 0, 0, 0], [0, 0, 0, 0, 0, 0, 0, 0, 0, 4, 0, 0, 0, 0, 0, 0, 0, 0, 0], [0, 0, 0, 8, 7, 0, 0, 0, 0, 4, 0, 0, 0, 8, 7, 0, 0, 0, 0], [0, 0, 0, 0, 8, 0, 0, 3, 0, 4, 0, 0, 0, 0, 8, 0, 0, 3, 0], [0, 7, 0, 0, 0, 0, 0, 0, 0, 4, 0, 7, 0, 0, 0, 0, 0, 0, 0], [4, 4, 4, 4, 4, 4, 4, 4, 4, 4, 4, 4, 4, 4, 4, 4, 4, 4, 4], [0, 0, 0, 0, 0, 0, 0, 0, 0, 4, 0, 0, 0, 0, 0, 0, 0, 0, 0], [0, 0, 0, 0, 0, 7, 0, 0, 0, 4, 0, 0, 0, 0, 0, 7, 0, 0, 0], [0, 0, 0, 2, 0, 0, 0, 0, 0, 4, 0, 0, 0, 2, 0, 0, 0, 0, 0], [0, 0, 2, 0, 0, 0, 0, 0, 0, 4, 0, 0, 2, 0, 0, 0, 0, 0, 0], [0, 3, 0, 0, 0, 3, 0, 0, 0, 4, 0, 3, 0, 0, 0, 3, 0, 0, 0], [0, 0, 0, 0, 0, 0, 0, 0, 0, 4, 0, 0, 0, 0, 0, 0, 0, 0, 0], [0, 0, 0, 8, 7, 0, 0, 0, 0, 4, 0, 0, 0, 8, 7, 0, 0, 0, 0], [0, 0, 0, 0, 8, 0, 0, 3, 0, 4, 0, 0, 0, 0, 8, 0, 0, 3, 0], [0, 7, 0, 0, 0, 0, 0, 0, 0, 4, 0, 7, 0, 0, 0, 0, 0, 0, 0]]}], "test_examples": [{"input": [[0, 0, 0, 0, 0, 0, 0, 0, 0, 4, 0, 0, 0, 0, 0, 0, 0, 0, 0, 4, 0, 0, 0, 0, 0, 0, 0, 0, 0], [0, 0, 0, 0, 0, 0, 0, 0, 0, 4, 0, 0, 0, 0, 3, 0, 0, 0, 0, 4, 0, 0, 0, 0, 0, 0, 0, 0, 0], [0, 0, 0, 0, 0, 0, 0, 0, 0, 4, 0, 2, 0, 0, 0, 0, 0, 2, 0, 4, 0, 0, 0, 0, 0, 0, 0, 0, 0], [0, 0, 0, 0, 0, 0, 0, 0, 0, 4, 0, 3, 0, 0, 0, 0, 0, 2, 0, 4, 0, 0, 0, 0, 0, 0, 0, 0, 0], [0, 0, 0, 0, 0, 0, 0, 0, 0, 4, 0, 0, 0, 0, 2, 0, 0, 0, 0, 4, 0, 0, 0, 0, 0, 0, 0, 0, 0], [0, 0, 0, 0, 0, 0, 0, 0, 0, 4, 0, 0, 0, 0, 0, 0, 0, 0, 0, 4, 0, 0, 0, 0, 0, 0, 0, 0, 0], [0, 0, 0, 0, 0, 0, 0, 0, 0, 4, 0, 0, 6, 0, 0, 0, 0, 0, 0, 4, 0, 0, 0, 0, 0, 0, 0, 0, 0], [0, 0, 0, 0, 0, 0, 0, 0, 0, 4, 0, 0, 0, 0, 0, 0, 0, 0, 0, 4, 0, 0, 0, 0, 0, 0, 0, 0, 0], [0, 0, 0, 0, 0, 0, 0, 0, 0, 4, 0, 0, 0, 0, 0, 0, 6, 0, 0, 4, 0, 0, 0, 0, 0, 0, 0, 0, 0], [4, 4, 4, 4, 4, 4, 4, 4, 4, 4, 4, 4, 4, 4, 4, 4, 4, 4, 4, 4, 4, 4, 4, 4, 4, 4, 4, 4, 4], [0, 0, 0, 0, 0, 0, 0, 0, 0, 4, 0, 0, 0, 0, 0, 0, 0, 0, 0, 4, 0, 0, 0, 0, 0, 0, 0, 0, 0], [0, 0, 0, 0, 0, 0, 0, 0, 0, 4, 0, 0, 0, 0, 0, 0, 0, 0, 0, 4, 0, 0, 0, 0, 0, 0, 0, 0, 0], [0, 0, 0, 0, 0, 0, 0, 0, 0, 4, 0, 0, 0, 0, 0, 0, 0, 0, 0, 4, 0, 0, 0, 0, 0, 0, 0, 0, 0], [0, 0, 0, 0, 0, 0, 0, 0, 0, 4, 0, 0, 0, 0, 0, 0, 0, 0, 0, 4, 0, 0, 0, 0, 0, 0, 0, 0, 0], [0, 0, 0, 0, 0, 0, 0, 0, 0, 4, 0, 0, 0, 0, 0, 0, 0, 0, 0, 4, 0, 0, 0, 0, 0, 0, 0, 0, 0], [0, 0, 0, 0, 0, 0, 0, 0, 0, 4, 0, 0, 0, 0, 0, 0, 0, 0, 0, 4, 0, 0, 0, 0, 0, 0, 0, 0, 0], [0, 0, 0, 0, 0, 0, 0, 0, 0, 4, 0, 0, 0, 0, 0, 0, 0, 0, 0, 4, 0, 0, 0, 0, 0, 0, 0, 0, 0], [0, 0, 0, 0, 0, 0, 0, 0, 0, 4, 0, 0, 0, 0, 0, 0, 0, 0, 0, 4, 0, 0, 0, 0, 0, 0, 0, 0, 0], [0, 0, 0, 0, 0, 0, 0, 0, 0, 4, 0, 0, 0, 0, 0, 0, 0, 0, 0, 4, 0, 0, 0, 0, 0, 0, 0, 0, 0]], "output": [[0, 0, 0, 0, 0, 0, 0, 0, 0, 4, 0, 0, 0, 0, 0, 0, 0, 0, 0, 4, 0, 0, 0, 0, 0, 0, 0, 0, 0], [0, 0, 0, 0, 3, 0, 0, 0, 0, 4, 0, 0, 0, 0, 3, 0, 0, 0, 0, 4, 0, 0, 0, 0, 3, 0, 0, 0, 0], [0, 2, 0, 0, 0, 0, 0, 2, 0, 4, 0, 2, 0, 0, 0, 0, 0, 2, 0, 4, 0, 2, 0, 0, 0, 0, 0, 2, 0], [0, 3, 0, 0, 0, 0, 0, 2, 0, 4, 0, 3, 0, 0, 0, 0, 0, 2, 0, 4, 0, 3, 0, 0, 0, 0, 0, 2, 0], [0, 0, 0, 0, 2, 0, 0, 0, 0, 4, 0, 0, 0, 0, 2, 0, 0, 0, 0, 4, 0, 0, 0, 0, 2, 0, 0, 0, 0], [0, 0, 0, 0, 0, 0, 0, 0, 0, 4, 0, 0, 0, 0, 0, 0, 0, 0, 0, 4, 0, 0, 0, 0, 0, 0, 0, 0, 0], [0, 0, 6, 0, 0, 0, 0, 0, 0, 4, 0, 0, 6, 0, 0, 0, 0, 0, 0, 4, 0, 0, 6, 0, 0, 0, 0, 0, 0], [0, 0, 0, 0, 0, 0, 0, 0, 0, 4, 0, 0, 0, 0, 0, 0, 0, 0, 0, 4, 0, 0, 0, 0, 0, 0, 0, 0, 0], [0, 0, 0, 0, 0, 0, 6, 0, 0, 4, 0, 0, 0, 0, 0, 0, 6, 0, 0, 4, 0, 0, 0, 0, 0, 0, 6, 0, 0], [4, 4, 4, 4, 4, 4, 4, 4, 4, 4, 4, 4, 4, 4, 4, 4, 4, 4, 4, 4, 4, 4, 4, 4, 4, 4, 4, 4, 4], [0, 0, 0, 0, 0, 0, 0, 0, 0, 4, 0, 0, 0, 0, 0, 0, 0, 0, 0, 4, 0, 0, 0, 0, 0, 0, 0, 0, 0], [0, 0, 0, 0, 3, 0, 0, 0, 0, 4, 0, 0, 0, 0, 3, 0, 0, 0, 0, 4, 0, 0, 0, 0, 3, 0, 0, 0, 0], [0, 2, 0, 0, 0, 0, 0, 2, 0, 4, 0, 2, 0, 0, 0, 0, 0, 2, 0, 4, 0, 2, 0, 0, 0, 0, 0, 2, 0], [0, 3, 0, 0, 0, 0, 0, 2, 0, 4, 0, 3, 0, 0, 0, 0, 0, 2, 0, 4, 0, 3, 0, 0, 0, 0, 0, 2, 0], [0, 0, 0, 0, 2, 0, 0, 0, 0, 4, 0, 0, 0, 0, 2, 0, 0, 0, 0, 4, 0, 0, 0, 0, 2, 0, 0, 0, 0], [0, 0, 0, 0, 0, 0, 0, 0, 0, 4, 0, 0, 0, 0, 0, 0, 0, 0, 0, 4, 0, 0, 0, 0, 0, 0, 0, 0, 0], [0, 0, 6, 0, 0, 0, 0, 0, 0, 4, 0, 0, 6, 0, 0, 0, 0, 0, 0, 4, 0, 0, 6, 0, 0, 0, 0, 0, 0], [0, 0, 0, 0, 0, 0, 0, 0, 0, 4, 0, 0, 0, 0, 0, 0, 0, 0, 0, 4, 0, 0, 0, 0, 0, 0, 0, 0, 0], [0, 0, 0, 0, 0, 0, 6, 0, 0, 4, 0, 0, 0, 0, 0, 0, 6, 0, 0, 4, 0, 0, 0, 0, 0, 0, 6, 0, 0]]}], "task_key": "c444b776", "extra_info": ""}