{"program": "def solve_fcc82909(I):\n    x1 = objects(I, F, T, T)\n    x2 = rbind(add, DOWN)\n    x3 = compose(x2, llcorner)\n    x4 = compose(toivec, numcolors)\n    x5 = fork(add, lrcorner, x4)\n    x6 = fork(astuple, x3, x5)\n    x7 = compose(box, x6)\n    x8 = mapply(x7, x1)\n    O = fill(I, THREE, x8)\n    return O\n", "training_examples": [{"input": [[0, 0, 0, 0, 0, 0, 0, 0, 0, 0], [0, 0, 0, 0, 0, 0, 0, 0, 0, 0], [0, 9, 9, 0, 0, 0, 0, 0, 0, 0], [0, 6, 6, 0, 0, 0, 0, 0, 0, 0], [0, 0, 0, 0, 0, 0, 0, 0, 0, 0], [0, 0, 0, 0, 0, 8, 4, 0, 0, 0], [0, 0, 0, 0, 0, 7, 7, 0, 0, 0], [0, 0, 0, 0, 0, 0, 0, 0, 0, 0], [0, 0, 0, 0, 0, 0, 0, 0, 0, 0], [0, 0, 0, 0, 0, 0, 0, 0, 0, 0]], "output": [[0, 0, 0, 0, 0, 0, 0, 0, 0, 0], [0, 0, 0, 0, 0, 0, 0, 0, 0, 0], [0, 9, 9, 0, 0, 0, 0, 0, 0, 0], [0, 6, 6, 0, 0, 0, 0, 0, 0, 0], [0, 3, 3, 0, 0, 0, 0, 0, 0, 0], [0, 3, 3, 0, 0, 8, 4, 0, 0, 0], [0, 0, 0, 0, 0, 7, 7, 0, 0, 0], [0, 0, 0, 0, 0, 3, 3, 0, 0, 0], [0, 0, 0, 0, 0, 3, 3, 0, 0, 0], [0, 0, 0, 0, 0, 3, 3, 0, 0, 0]]}, {"input": [[0, 0, 0, 0, 0, 0, 0, 0, 0, 0], [0, 0, 4, 8, 0, 0, 0, 0, 0, 0], [0, 0, 9, 4, 0, 0, 0, 0, 0, 0], [0, 0, 0, 0, 0, 0, 0, 0, 0, 0], [0, 0, 0, 0, 0, 0, 2, 1, 0, 0], [0, 0, 0, 0, 0, 0, 1, 2, 0, 0], [0, 0, 0, 0, 0, 0, 0, 0, 0, 0], [0, 0, 0, 0, 0, 0, 0, 0, 0, 0], [0, 0, 0, 0, 0, 0, 0, 0, 0, 0], [0, 0, 0, 0, 0, 0, 0, 0, 0, 0]], "output": [[0, 0, 0, 0, 0, 0, 0, 0, 0, 0], [0, 0, 4, 8, 0, 0, 0, 0, 0, 0], [0, 0, 9, 4, 0, 0, 0, 0, 0, 0], [0, 0, 3, 3, 0, 0, 0, 0, 0, 0], [0, 0, 3, 3, 0, 0, 2, 1, 0, 0], [0, 0, 3, 3, 0, 0, 1, 2, 0, 0], [0, 0, 0, 0, 0, 0, 3, 3, 0, 0], [0, 0, 0, 0, 0, 0, 3, 3, 0, 0], [0, 0, 0, 0, 0, 0, 0, 0, 0, 0], [0, 0, 0, 0, 0, 0, 0, 0, 0, 0]]}, {"input": [[0, 0, 0, 0, 0, 0, 0, 0, 0, 0], [0, 0, 2, 4, 0, 0, 9, 8, 0, 0], [0, 0, 6, 7, 0, 0, 8, 9, 0, 0], [0, 0, 0, 0, 0, 0, 0, 0, 0, 0], [0, 0, 0, 0, 0, 0, 0, 0, 0, 0], [0, 0, 0, 0, 7, 6, 0, 0, 0, 0], [0, 0, 0, 0, 6, 6, 0, 0, 0, 0], [0, 0, 0, 0, 0, 0, 0, 0, 0, 0], [0, 0, 0, 0, 0, 0, 0, 0, 0, 0], [0, 0, 0, 0, 0, 0, 0, 0, 0, 0]], "output": [[0, 0, 0, 0, 0, 0, 0, 0, 0, 0], [0, 0, 2, 4, 0, 0, 9, 8, 0, 0], [0, 0, 6, 7, 0, 0, 8, 9, 0, 0], [0, 0, 3, 3, 0, 0, 3, 3, 0, 0], [0, 0, 3, 3, 0, 0, 3, 3, 0, 0], [0, 0, 3, 3, 7, 6, 0, 0, 0, 0], [0, 0, 3, 3, 6, 6, 0, 0, 0, 0], [0, 0, 0, 0, 3, 3, 0, 0, 0, 0], [0, 0, 0, 0, 3, 3, 0, 0, 0, 0], [0, 0, 0, 0, 0, 0, 0, 0, 0, 0]]}], "test_examples": [{"input": [[0, 0, 0, 0, 0, 0, 0, 0, 0, 0], [1, 1, 0, 0, 0, 0, 2, 9, 0, 0], [2, 1, 0, 0, 0, 0, 1, 6, 0, 0], [0, 0, 0, 4, 7, 0, 0, 0, 0, 0], [0, 0, 0, 8, 4, 0, 0, 0, 0, 0], [0, 0, 0, 0, 0, 0, 0, 0, 0, 0], [0, 0, 0, 0, 0, 0, 0, 0, 0, 0], [0, 0, 0, 0, 0, 0, 0, 0, 0, 0], [0, 0, 0, 0, 0, 0, 0, 0, 0, 0], [0, 0, 0, 0, 0, 0, 0, 0, 0, 0]], "output": [[0, 0, 0, 0, 0, 0, 0, 0, 0, 0], [1, 1, 0, 0, 0, 0, 2, 9, 0, 0], [2, 1, 0, 0, 0, 0, 1, 6, 0, 0], [3, 3, 0, 4, 7, 0, 3, 3, 0, 0], [3, 3, 0, 8, 4, 0, 3, 3, 0, 0], [0, 0, 0, 3, 3, 0, 3, 3, 0, 0], [0, 0, 0, 3, 3, 0, 3, 3, 0, 0], [0, 0, 0, 3, 3, 0, 0, 0, 0, 0], [0, 0, 0, 0, 0, 0, 0, 0, 0, 0], [0, 0, 0, 0, 0, 0, 0, 0, 0, 0]]}], "task_key": "fcc82909", "extra_info": ""}